README.rst
setup.py
email_filter/__init__.py
email_filter/admin.py
email_filter/mail_route.py
email_filter/models.py
email_filter/signal_processors.py
email_filter/signals.py
email_filter/urls.py
email_filter/utils.py
email_filter/wsgi.py
email_filter.egg-info/PKG-INFO
email_filter.egg-info/SOURCES.txt
email_filter.egg-info/dependency_links.txt
email_filter.egg-info/not-zip-safe
email_filter.egg-info/requires.txt
email_filter.egg-info/top_level.txt
email_filter/migrations/0001_initial.py
email_filter/migrations/0002_auto__add_field_emaillog_raw_email__add_field_emaillog_message_id__add.py
email_filter/migrations/0003_auto__add_emailattachment.py
email_filter/migrations/__init__.py