Metadata-Version: 1.0
Name: email-filter
Version: 0.2.8
Summary: Adds the script, which process given emails to proxy them, replacing real email addresses by company's local ones taken from the contrib.auth module.
Home-page: https://kavahq.com/42-coffee-cups/project/42-emailfilter/
Author: 42 Coffee Cups
Author-email: email_filter@42cc.co
License: BSD(?) licence, see LICENCE.txt
Platform: UNKNOWN
